Workbook

Sheet Historical Financial Data
B3: Particulars | C3: FY21 (Ref.) | D3: FY22 | E3: FY23 | F3: FY24 | G3: FY25 | H3: FY26
B4: Income Statement
B5: Revenue from Operations | C5: 21712.79 | D5: 29101.28 | E5: 34488.59 | F5: 35494.73 | G5: 33905.62 | H5: 35583.54
B6: EBITDA / Operating Profit | C6: 5158.65 | D6: 5183.62 | E6: 6646.32 | F6: 8272.94 | G6: 6578.82 | H6: 7419.72
B7: Depreciation & Amortisation | C7: 791.27 | D7: 816.36 | E7: 858.02 | F7: 853 | G7: 1026.34 | H7: 1228.85
B8: EBIT | C8: =C6-C7 -> 4367.38 | D8: =D6-D7 -> 4367.26 | E8: =E6-E7 -> 5788.3 | F8: =F6-F7 -> 7419.94 | G8: =G6-G7 -> 5552.48 | H8: =H6-H7 -> 6190.87
B9: Finance Cost | C9: 91.63 | D9: 95.41 | E9: 144.45 | F9: 205.17 | G9: 227.02 | H9: 195.41
B10: Profit Before Tax (PBT) | C10: 4304.35 | D10: 4187.72 | E10: 5688.83 | F10: 7347.77 | G10: 5103.07 | H10: 6003.44
B11: Tax Expense | C11: 1097.6 | D11: 1102.91 | E11: 1493.5 | F11: 1790.08 | G11: 1393.36 | H11: 1608.75
B12: Profit After Tax (PAT) | C12: 3206.75 | D12: 3084.81 | E12: 4195.33 | F12: 5557.69 | G12: 3709.71 | H12: 4394.69
B14: Cash Flow Items
B15: Cash Flow from Operations (CFO) | C15: 3683.35 | D15: 986.49 | E15: 4193.43 | F15: 6103.6 | G15: 4423.96 | H15: 7088.18
B16: Capital Expenditure (CapEx) | C16: 281.87 | D16: 538.24 | E16: 1273.37 | F16: 2199.01 | G16: 1805.32 | H16: 1467.02
B17: Change in Net Working Capital | D17: =(D21-D22)-(C21-C22) -> 1480.6 | E17: =(E21-E22)-(D21-D22) -> 1057.89 | F17: =(F21-F22)-(E21-E22) -> 396.87 | G17: =(G21-G22)-(F21-F22) -> -185.65 | H17: =(H21-H22)-(G21-G22) -> 2197.16
B19: Balance Sheet Items
B20: Net Fixed Assets / PP&E | C20: 4476.35 | D20: 4184.46 | E20: 4145.65 | F20: 4446.2 | G20: 6787.62 | H20: 7146.23
B21: Current Assets | C21: 12026.6 | D21: 15152.33 | E21: 16535.16 | F21: 17537.06 | G21: 16991.68 | H21: 20184.64
B22: Current Liabilities | C22: 5925.86 | D22: 7570.99 | E22: 7895.93 | F22: 8500.96 | G22: 8141.23 | H22: 9137.03
B23: Total Debt | C23: 348.58 | D23: 775.66 | E23: 972.21 | F23: 1107.14 | G23: 863.75 | H23: 2293.26
B24: Cash & Cash Equivalents | C24: 346.39 | D24: 621.72 | E24: 523.1 | F24: 829.34 | G24: 445.28 | H24: 672.83
B25: Total Equity | C25: 13229.15 | D25: 14199.09 | E25: 16445.89 | F25: 19423.68 | G25: 20059.05 | H25: 22014.98
B26: Shares Outstanding (Crore) | C26: 95.92 | D26: 95.92 | E26: 95.92 | F26: 95.92 | G26: 95.92 | H26: 95.92
B27: nwc | D27: =D21-D22 -> 7581.34 | E27: =E21-E22 -> 8639.23 | F27: =F21-F22 -> 9036.1 | G27: =G21-G22 -> 8850.45 | H27: =H21-H22 -> 11047.61
B28: Key Ratios (Calculated)
B29: EBIT Margin (%) | C29: =IFERROR(C8/C5,"-") -> 0.2011432 | D29: =IFERROR(D8/D5,"-") -> 0.15007106 | E29: =IFERROR(E8/E5,"-") -> 0.16783232 | F29: =IFERROR(F8/F5,"-") -> 0.20904343 | G29: =IFERROR(G8/G5,"-") -> 0.16376282 | H29: =IFERROR(H8/H5,"-") -> 0.17398128
B30: EBITDA Margin (%) | C30: =IFERROR(C6/C5,"-") -> 0.23758577 | D30: =IFERROR(D6/D5,"-") -> 0.17812344 | E30: =IFERROR(E6/E5,"-") -> 0.19271069 | F30: =IFERROR(F6/F5,"-") -> 0.23307516 | G30: =IFERROR(G6/G5,"-") -> 0.19403332 | H30: =IFERROR(H6/H5,"-") -> 0.20851551
B31: Tax Rate (%) | C31: =IFERROR(C11/C10,"-") -> 0.25499785 | D31: =IFERROR(D11/D10,"-") -> 0.26336766 | E31: =IFERROR(E11/E10,"-") -> 0.26253201 | F31: =IFERROR(F11/F10,"-") -> 0.24362221 | G31: =IFERROR(G11/G10,"-") -> 0.27304348 | H31: =IFERROR(H11/H10,"-") -> 0.26797136
B32: CapEx % of Revenue | C32: =IFERROR(C16/C5,"-") -> 0.012981749 | D32: =IFERROR(D16/D5,"-") -> 0.018495406 | E32: =IFERROR(E16/E5,"-") -> 0.036921486 | F32: =IFERROR(F16/F5,"-") -> 0.061953141 | G32: =IFERROR(G16/G5,"-") -> 0.05324545 | H32: =IFERROR(H16/H5,"-") -> 0.041227489
B33: Revenue Growth (%) | D33: =IFERROR(D5/C5-1,"-") -> 0.34028285 | E33: =IFERROR(E5/D5-1,"-") -> 0.18512278 | F33: =IFERROR(F5/E5-1,"-") -> 0.029173127 | G33: =IFERROR(G5/F5-1,"-") -> -0.044770308 | H33: =IFERROR(H5/G5-1,"-") -> 0.049487961

Sheet Assumptions
B3: Assumptions | C3: FY27E | D3: FY28E | E3: FY29E | F3: FY30E | G3: FY31E
B4: Revenue Growth | C4: 0.07 | D4: 0.065 | E4: 0.06 | F4: 0.055 | G4: 0.05
B5: EBITDA Margin | C5: 0.21 | D5: 0.21 | E5: 0.21 | F5: 0.21 | G5: 0.21
B6: EBIT MARGIN | C6: 0.175 | D6: 0.175 | E6: 0.175 | F6: 0.175 | G6: 0.175
B7: TAX RATE | C7: 0.265 | D7: 0.265 | E7: 0.265 | F7: 0.265 | G7: 0.265
B8: CAPEX % REVENUE | C8: 0.04 | D8: 0.04 | E8: 0.04 | F8: 0.04 | G8: 0.04
B9: D & A % REVENUE | C9: 0.035 | D9: 0.035 | E9: 0.035 | F9: 0.035 | G9: 0.035
B10: % NET WORKING CAPITAL | C10: 0.25 | D10: 0.25 | E10: 0.25 | F10: 0.25 | G10: 0.25

Sheet WACC
B3: Cost of Equity
B4: Risk-Free Rate | C4: 0.07
B5: Stock Beta | C5: 0.85
B6: Equity Risk Premium | C6: 0.06
B7: Cost of Equity | C7: =C4+(C5*C6) -> 0.121
B9: cost of debt
B10: total debt | C10: ='Historical Financial Data'!H23 -> 2293.26
B11: interest exp | C11: ='Historical Financial Data'!H9 -> 195.41
B12: effective tax rate | C12: =Assumptions!C7 -> 0.265
B13: pre tax cost of capital | C13: =C11/C10 -> 0.085210574
B14: Post-Tax Cost of Debt | C14: =C13*(1-C12) -> 0.062629772
B16: Capital Structure Weights
B17: Current Market Cap (Equity Value) | C17: 234430
B18: total debt | C18: =C10 -> 2293.26
B19: Total Capitalization | C19: =C17+C18 -> 236723.26
B20: weight of equity | C20: =C17/C19 -> 0.99031249
B21: weight of Debt | C21: =C18/C19 -> 0.0096875144
B23: WACC | C23: =(C20*C7)+(C21*C14) -> 0.12043454

Sheet forecast
C2: FY27E | D2: FY28E | E2: FY29E | F2: FY30E | G2: FY31E
B3: REVENUE | C3: ='Historical Financial Data'!H5*(1+forecast!C4) -> 38074.388 | D3: =C3*(1+D4) -> 40549.223 | E3: =D3*(1+E4) -> 42982.176 | F3: =E3*(1+F4) -> 45346.196 | G3: =F3*(1+G4) -> 47613.506
B4: REVENUE GROWTH | C4: =Assumptions!C4 -> 0.07 | D4: =Assumptions!D4 -> 0.065 | E4: =Assumptions!E4 -> 0.06 | F4: =Assumptions!F4 -> 0.055 | G4: =Assumptions!G4 -> 0.05
B5: EBIDTA | C5: =C3*C6 -> 7995.6214 | D5: =D3*D6 -> 8515.3368 | E5: =E3*E6 -> 9026.257 | F5: =F3*F6 -> 9522.7012 | G5: =G3*G6 -> 9998.8362
B6: EBITDA MARGIN | C6: =Assumptions!C5 -> 0.21 | D6: =Assumptions!D5 -> 0.21 | E6: =Assumptions!E5 -> 0.21 | F6: =Assumptions!F5 -> 0.21 | G6: =Assumptions!G5 -> 0.21
B7: D&A | C7: =C3*Assumptions!C9 -> 1332.6036 | D7: =D3*Assumptions!D9 -> 1419.2228 | E7: =E3*Assumptions!E9 -> 1504.3762 | F7: =F3*Assumptions!F9 -> 1587.1169 | G7: =G3*Assumptions!G9 -> 1666.4727
B8: EBIT | C8: =C5-C7 -> 6663.0179 | D8: =D5-D7 -> 7096.114 | E8: =E5-E7 -> 7521.8809 | F8: =F5-F7 -> 7935.5843 | G8: =G5-G7 -> 8332.3635
B9: EBIT MARGIN | C9: =C8/C3 -> 0.175 | D9: =D8/D3 -> 0.175 | E9: =E8/E3 -> 0.175 | F9: =F8/F3 -> 0.175 | G9: =G8/G3 -> 0.175
B10: TAX | C10: =C8*Assumptions!C7 -> 1765.6997 | D10: =D8*Assumptions!D7 -> 1880.4702 | E10: =E8*Assumptions!E7 -> 1993.2984 | F10: =F8*Assumptions!F7 -> 2102.9298 | G10: =G8*Assumptions!G7 -> 2208.0763
B11: NOPAT | C11: =C8-C10 -> 4897.3181 | D11: =D8-D10 -> 5215.6438 | E11: =E8-E10 -> 5528.5824 | F11: =F8-F10 -> 5832.6545 | G11: =G8-G10 -> 6124.2872
B12: CAPEX | C12: =C3*Assumptions!C8 -> 1522.9755 | D12: =D3*Assumptions!D8 -> 1621.9689 | E12: =E3*Assumptions!E8 -> 1719.2871 | F12: =F3*Assumptions!F8 -> 1813.8478 | G12: =G3*Assumptions!G8 -> 1904.5402
B13: CHANGE IN NWC | C13: =(C3*Assumptions!C10) - ('Historical Financial Data'!$H$21-'Historical Financial Data'!H22) -> -1529.013 | D13: =(D3*Assumptions!D10)-(forecast!C3*Assumptions!C10) -> 618.7088 | E13: =(E3*Assumptions!E10)-(forecast!D3*Assumptions!D10) -> 608.23835 | F13: =(F3*Assumptions!F10)-(forecast!E3*Assumptions!E10) -> 591.00493 | G13: =(G3*Assumptions!G10)-(forecast!F3*Assumptions!F10) -> 566.82745
B14: FCFF | C14: =C11+C7-C12-(C13) -> 6235.9592 | D14: =D11+D7-D12-D13 -> 4394.1889 | E14: =E11+E7-E12-E13 -> 4705.4332 | F14: =F11+F7-F12-F13 -> 5014.9186 | G14: =G11+G7-G12-G13 -> 5319.3922
B15: WACC | C15: =WACC!$C$23 -> 0.12043454 | D15: =WACC!$C$23 -> 0.12043454 | E15: =WACC!$C$23 -> 0.12043454 | F15: =WACC!$C$23 -> 0.12043454 | G15: =WACC!$C$23 -> 0.12043454
B16: DISCOUNT FACTOR | C16: =1/(1+C15)^1 -> 0.89251087 | D16: =1/(1+D15)^2 -> 0.79657565 | E16: =1/(1+E15)^3 -> 0.71095242 | F16: =1/(1+F15)^4 -> 0.63453276 | G16: =1/(1+G15)^5 -> 0.56632738
B17: PV OF FCFF | C17: =C14*C16 -> 5565.6614 | D17: =D14*D16 -> 3500.3039 | E17: =E14*E16 -> 3345.3391 | F17: =F14*F16 -> 3182.1301 | G17: =G14*G16 -> 3012.5175
B18: terminal growth rate | C18: 0.04 | D18: 0.04 | E18: 0.04 | F18: 0.04 | G18: 0.04
B19: terminal value | G19: =(G14*(1+G18))/(G15-G18) -> 68778.513
B20: pv of terminal value | C20: =C19*G16 -> 0 | G20: =G19*G16 -> 38951.155
B21: enterprise value | C21: =SUM(C17:G17)+G20 -> 57557.107
B22: less : debt | C22: ='Historical Financial Data'!H23 -> 2293.26
B23: Add: cash | C23: ='Historical Financial Data'!H24 -> 672.83
B24: Equity value | C24: =C21-C22+C23 -> 55936.677
B25: shares outstanding | C25: ='Historical Financial Data'!H26 -> 95.92
B26: implied share price | C26: =C24/C25 -> 583.15969

Sheet Sensitivity Analysis
B2: WACC/TERMINAL GROWTH
C3: 0.03 | D3: 0.035 | E3: 0.04 | F3: 0.045 | G3: 0.05
B4: 0.11 | C4: =(forecast!$C$14/(1+$B4)^1+forecast!$D$14/(1+$B4)^2+forecast!$E$14/(1+$B4)^3+forecast!$F$14/(1+$B4)^4+forecast!$G$14/(1+$B4)^5+forecast!$G$14*(1+C$3)/(($B4-C$3)*(1+$B4)^5)-forecast!$C$22+forecast!$C$23)/forecast!$C$25 -> 605.8031 | D4: =(forecast!$C$14/(1+$B4)^1+forecast!$D$14/(1+$B4)^2+forecast!$E$14/(1+$B4)^3+forecast!$F$14/(1+$B4)^4+forecast!$G$14/(1+$B4)^5+forecast!$G$14*(1+D$3)/(($B4-D$3)*(1+$B4)^5)-forecast!$C$22+forecast!$C$23)/forecast!$C$25 -> 636.24555 | E4: =(forecast!$C$14/(1+$B4)^1+forecast!$D$14/(1+$B4)^2+forecast!$E$14/(1+$B4)^3+forecast!$F$14/(1+$B4)^4+forecast!$G$14/(1+$B4)^5+forecast!$G$14*(1+E$3)/(($B4-E$3)*(1+$B4)^5)-forecast!$C$22+forecast!$C$23)/forecast!$C$25 -> 671.03693 | F4: =(forecast!$C$14/(1+$B4)^1+forecast!$D$14/(1+$B4)^2+forecast!$E$14/(1+$B4)^3+forecast!$F$14/(1+$B4)^4+forecast!$G$14/(1+$B4)^5+forecast!$G$14*(1+F$3)/(($B4-F$3)*(1+$B4)^5)-forecast!$C$22+forecast!$C$23)/forecast!$C$25 -> 711.18083 | G4: =(forecast!$C$14/(1+$B4)^1+forecast!$D$14/(1+$B4)^2+forecast!$E$14/(1+$B4)^3+forecast!$F$14/(1+$B4)^4+forecast!$G$14/(1+$B4)^5+forecast!$G$14*(1+G$3)/(($B4-G$3)*(1+$B4)^5)-forecast!$C$22+forecast!$C$23)/forecast!$C$25 -> 758.01538
B5: 0.115 | C5: =(forecast!$C$14/(1+$B5)^1+forecast!$D$14/(1+$B5)^2+forecast!$E$14/(1+$B5)^3+forecast!$F$14/(1+$B5)^4+forecast!$G$14/(1+$B5)^5+forecast!$G$14*(1+C$3)/(($B5-C$3)*(1+$B5)^5)-forecast!$C$22+forecast!$C$23)/forecast!$C$25 -> 569.59547 | D5: =(forecast!$C$14/(1+$B5)^1+forecast!$D$14/(1+$B5)^2+forecast!$E$14/(1+$B5)^3+forecast!$F$14/(1+$B5)^4+forecast!$G$14/(1+$B5)^5+forecast!$G$14*(1+D$3)/(($B5-D$3)*(1+$B5)^5)-forecast!$C$22+forecast!$C$23)/forecast!$C$25 -> 595.97788 | E5: =(forecast!$C$14/(1+$B5)^1+forecast!$D$14/(1+$B5)^2+forecast!$E$14/(1+$B5)^3+forecast!$F$14/(1+$B5)^4+forecast!$G$14/(1+$B5)^5+forecast!$G$14*(1+E$3)/(($B5-E$3)*(1+$B5)^5)-forecast!$C$22+forecast!$C$23)/forecast!$C$25 -> 625.87794 | F5: =(forecast!$C$14/(1+$B5)^1+forecast!$D$14/(1+$B5)^2+forecast!$E$14/(1+$B5)^3+forecast!$F$14/(1+$B5)^4+forecast!$G$14/(1+$B5)^5+forecast!$G$14*(1+F$3)/(($B5-F$3)*(1+$B5)^5)-forecast!$C$22+forecast!$C$23)/forecast!$C$25 -> 660.04944 | G5: =(forecast!$C$14/(1+$B5)^1+forecast!$D$14/(1+$B5)^2+forecast!$E$14/(1+$B5)^3+forecast!$F$14/(1+$B5)^4+forecast!$G$14/(1+$B5)^5+forecast!$G$14*(1+G$3)/(($B5-G$3)*(1+$B5)^5)-forecast!$C$22+forecast!$C$23)/forecast!$C$25 -> 699.4781
B6: 0.1204 | C6: =(forecast!$C$14/(1+$B6)^1+forecast!$D$14/(1+$B6)^2+forecast!$E$14/(1+$B6)^3+forecast!$F$14/(1+$B6)^4+forecast!$G$14/(1+$B6)^5+forecast!$G$14*(1+C$3)/(($B6-C$3)*(1+$B6)^5)-forecast!$C$22+forecast!$C$23)/forecast!$C$25 -> 534.9917 | D6: =(forecast!$C$14/(1+$B6)^1+forecast!$D$14/(1+$B6)^2+forecast!$E$14/(1+$B6)^3+forecast!$F$14/(1+$B6)^4+forecast!$G$14/(1+$B6)^5+forecast!$G$14*(1+D$3)/(($B6-D$3)*(1+$B6)^5)-forecast!$C$22+forecast!$C$23)/forecast!$C$25 -> 557.78484 | E6: =(forecast!$C$14/(1+$B6)^1+forecast!$D$14/(1+$B6)^2+forecast!$E$14/(1+$B6)^3+forecast!$F$14/(1+$B6)^4+forecast!$G$14/(1+$B6)^5+forecast!$G$14*(1+E$3)/(($B6-E$3)*(1+$B6)^5)-forecast!$C$22+forecast!$C$23)/forecast!$C$25 -> 583.41295 | F6: =(forecast!$C$14/(1+$B6)^1+forecast!$D$14/(1+$B6)^2+forecast!$E$14/(1+$B6)^3+forecast!$F$14/(1+$B6)^4+forecast!$G$14/(1+$B6)^5+forecast!$G$14*(1+F$3)/(($B6-F$3)*(1+$B6)^5)-forecast!$C$22+forecast!$C$23)/forecast!$C$25 -> 612.44001 | G6: =(forecast!$C$14/(1+$B6)^1+forecast!$D$14/(1+$B6)^2+forecast!$E$14/(1+$B6)^3+forecast!$F$14/(1+$B6)^4+forecast!$G$14/(1+$B6)^5+forecast!$G$14*(1+G$3)/(($B6-G$3)*(1+$B6)^5)-forecast!$C$22+forecast!$C$23)/forecast!$C$25 -> 645.59023
B7: 0.125 | C7: =(forecast!$C$14/(1+$B7)^1+forecast!$D$14/(1+$B7)^2+forecast!$E$14/(1+$B7)^3+forecast!$F$14/(1+$B7)^4+forecast!$G$14/(1+$B7)^5+forecast!$G$14*(1+C$3)/(($B7-C$3)*(1+$B7)^5)-forecast!$C$22+forecast!$C$23)/forecast!$C$25 -> 508.61856 | D7: =(forecast!$C$14/(1+$B7)^1+forecast!$D$14/(1+$B7)^2+forecast!$E$14/(1+$B7)^3+forecast!$F$14/(1+$B7)^4+forecast!$G$14/(1+$B7)^5+forecast!$G$14*(1+D$3)/(($B7-D$3)*(1+$B7)^5)-forecast!$C$22+forecast!$C$23)/forecast!$C$25 -> 528.8649 | E7: =(forecast!$C$14/(1+$B7)^1+forecast!$D$14/(1+$B7)^2+forecast!$E$14/(1+$B7)^3+forecast!$F$14/(1+$B7)^4+forecast!$G$14/(1+$B7)^5+forecast!$G$14*(1+E$3)/(($B7-E$3)*(1+$B7)^5)-forecast!$C$22+forecast!$C$23)/forecast!$C$25 -> 551.49317 | F7: =(forecast!$C$14/(1+$B7)^1+forecast!$D$14/(1+$B7)^2+forecast!$E$14/(1+$B7)^3+forecast!$F$14/(1+$B7)^4+forecast!$G$14/(1+$B7)^5+forecast!$G$14*(1+F$3)/(($B7-F$3)*(1+$B7)^5)-forecast!$C$22+forecast!$C$23)/forecast!$C$25 -> 576.94997 | G7: =(forecast!$C$14/(1+$B7)^1+forecast!$D$14/(1+$B7)^2+forecast!$E$14/(1+$B7)^3+forecast!$F$14/(1+$B7)^4+forecast!$G$14/(1+$B7)^5+forecast!$G$14*(1+G$3)/(($B7-G$3)*(1+$B7)^5)-forecast!$C$22+forecast!$C$23)/forecast!$C$25 -> 605.80101
B8: 0.13 | C8: =(forecast!$C$14/(1+$B8)^1+forecast!$D$14/(1+$B8)^2+forecast!$E$14/(1+$B8)^3+forecast!$F$14/(1+$B8)^4+forecast!$G$14/(1+$B8)^5+forecast!$G$14*(1+C$3)/(($B8-C$3)*(1+$B8)^5)-forecast!$C$22+forecast!$C$23)/forecast!$C$25 -> 482.70523 | D8: =(forecast!$C$14/(1+$B8)^1+forecast!$D$14/(1+$B8)^2+forecast!$E$14/(1+$B8)^3+forecast!$F$14/(1+$B8)^4+forecast!$G$14/(1+$B8)^5+forecast!$G$14*(1+D$3)/(($B8-D$3)*(1+$B8)^5)-forecast!$C$22+forecast!$C$23)/forecast!$C$25 -> 500.60657 | E8: =(forecast!$C$14/(1+$B8)^1+forecast!$D$14/(1+$B8)^2+forecast!$E$14/(1+$B8)^3+forecast!$F$14/(1+$B8)^4+forecast!$G$14/(1+$B8)^5+forecast!$G$14*(1+E$3)/(($B8-E$3)*(1+$B8)^5)-forecast!$C$22+forecast!$C$23)/forecast!$C$25 -> 520.49694 | F8: =(forecast!$C$14/(1+$B8)^1+forecast!$D$14/(1+$B8)^2+forecast!$E$14/(1+$B8)^3+forecast!$F$14/(1+$B8)^4+forecast!$G$14/(1+$B8)^5+forecast!$G$14*(1+F$3)/(($B8-F$3)*(1+$B8)^5)-forecast!$C$22+forecast!$C$23)/forecast!$C$25 -> 542.72736 | G8: =(forecast!$C$14/(1+$B8)^1+forecast!$D$14/(1+$B8)^2+forecast!$E$14/(1+$B8)^3+forecast!$F$14/(1+$B8)^4+forecast!$G$14/(1+$B8)^5+forecast!$G$14*(1+G$3)/(($B8-G$3)*(1+$B8)^5)-forecast!$C$22+forecast!$C$23)/forecast!$C$25 -> 567.73658

Sheet DCF valuation Summary
B2: DCF Valuation Summary,Value
B3: Enterprise Value, | C3: =forecast!C21 -> 57557.107
B4: Less: Debt, | C4: ='Historical Financial Data'!H23 -> 2293.26
B5: Add: Cash, | C5: ='Historical Financial Data'!H24 -> 672.83
B6: Equity Value, | C6: =forecast!C24 -> 55936.677
B7: Shares Outstanding, | C7: ='Historical Financial Data'!H26 -> 95.92
B8: Implied Share Price, | C8: =forecast!C26 -> 583.15969
B9: Current market price | C9: 2444
B10: Upside/downside % | C10: =(C8/C9)-1 -> -0.76139129
B11: Remark | C11: Overvalued
